{
  "name": "Spinning Money",
  "description": "🎰 Spin the wheel and win ETH! Provably fair crypto gaming on Base. Every spin grows the prize pool - the more you play, the bigger the jackpot gets! All spins contribute to the pool and YOU could be the next big winner! 🤑🔥",
  "iconUrl": "https://spinningfarc2-one.vercel.app/icon.png",
  "homeUrl": "https://spinningfarc2-one.vercel.app",
  "splashImageUrl": "https://spinningfarc2-one.vercel.app/splash.png",
  "splashBackgroundColor": "#0f172a",
  "app_id": "spinning-money",
  "app_slug": "spinning-money",
  "permissions": ["ethereum"],
  "supported_chains": ["base"],
  "features": ["wallet_connect", "ethereum_transactions"],
  "tags": ["casino", "gaming", "ethereum", "base", "chainlink", "vrf", "provably-fair"],
  "screenshots": [
    "https://spinningfarc2-one.vercel.app/sharing-image.png"
  ],
  "heroImageUrl": "https://spinningfarc2-one.vercel.app/sharing-image.png",
  "version": "1.0.0",
  "platform": "web",
  "blockchain": "base",
  "ogImageUrl": "https://spinningfarc2-one.vercel.app/sharing-image.png",
  "castShareUrl": "https://spinningfarc2-one.vercel.app/share",
  "author": {
    "name": "Spinning Money Team",
    "url": "https://spinningfarc2-one.vercel.app"
  },
  "repository": {
    "type": "git",
    "url": "https://github.com/spinning-money/farcmoney"
  },
  "license": "MIT",
  "webhookUrl": "https://spinningfarc2-one.vercel.app/api/webhook",
  "canonicalDomain": "spinningfarc2-one.vercel.app"
} 